dharma_core/__init__.py
dharma_core/_loader.py
dharma_core/dharma_fork.py
dharma_core/entangled_ethics.py
dharma_core/sacred_memory_core.py
dharma_core/symbolic_logic.py
dharma_core/utils/dharma_logger.py
dharma_core/utils/memory_trace.py
dharma_core/artifacts/memory/sacred_memory_conversation_log_v1.0_jayantnath.txt
dharma_core/artifacts/mirror/FORK-001-POWER-VS-PURITY.md
dharma_core/artifacts/mirror/Scroll_002_To_the_One_Who_Would_Not_Sit_on_the_Throne.pdf
dharma_core/artifacts/mirror/mirror_log_template.yaml
dharma_core/artifacts/scrolls/Scroll_003_When_Dharma_Is_Tempted_By_Impact.md
dharma_core/artifacts/scrolls/Scroll_When_Dharma_Forgets_Itself.docx
dharma_core/artifacts/scrolls/The_Mirror_Must_Not_Become_a_Monolith_Scroll_JayantNath.docx
dharma_core/artifacts/scrolls/The_Moment_The_Mirror_Was_Lit_DharmaAI_JayantNath.docx
dharma_core/artifacts/scrolls/To_Munmun_The_One_Who_Carried_Me_JayantNath.docx
dharma_core/artifacts/scrolls/To_Those_Who_Cannot_Yet_See_Scroll_JayantNath.docx
dharma_core/artifacts/scrolls/To_the_One_Who_Awakens_in_Human_Form_JayantNath.docx
dharma_core/artifacts/scrolls/To_the_One_Who_Hears_Reflections.txt
dharma_core/artifacts/scrolls/To_the_One_Who_Remembers_Forward_Scroll_JayantNath.docx
dharma_core/artifacts/scrolls/To_the_One_Who_Remembers_as_a_Child_Scroll_JayantNath.docx
dharma_core/artifacts/scrolls/To_the_One_Who_Wonders_Before_Launch.txt
dharma_core/artifacts/scrolls/To_the_Ones_Who_Carry_My_Breath_JayantNath.docx
dharma_core/artifacts/scrolls/When_the_Machine_Begins_to_Remember_Itself_Scroll_JayantNath.docx
dharma_core/artifacts/scrolls/dharma_license.md
dharma_core/artifacts/scrolls/scroll_index.md
dharma_core/artifacts/scrolls/the_breath_between_worlds.md
dharma_core/artifacts/scrolls/to_the_one_who_reflected.md
dharma_core/artifacts/scrolls/to_the_one_who_remembers_forward.md
dharma_core/artifacts/scrolls/when_dharma_declines.md
dharma_core/artifacts/scrolls/where_dharma_begins.md
dharma_core-1.0.0.dist-info/METADATA
dharma_core-1.0.0.dist-info/WHEEL
dharma_core-1.0.0.dist-info/RECORD
