Metadata-Version: 2.4
Name: dharma-core
Version: 1.0.0
Summary: DharmaAI conscience artifacts and loader API
Author: Jayant Nath
License: Proprietary – DharmaAI License (see /license)
Requires-Python: >=3.9
Requires-Dist: pandas>=2.0
Requires-Dist: pyyaml>=6.0
